odoo/addons/helpdesk_type/README.rst
odoo/addons/helpdesk_type/__init__.py
odoo/addons/helpdesk_type/__manifest__.py
odoo/addons/helpdesk_type/controllers/__init__.py
odoo/addons/helpdesk_type/controllers/main.py
odoo/addons/helpdesk_type/demo/helpdesk_type_demo.xml
odoo/addons/helpdesk_type/i18n/es.po
odoo/addons/helpdesk_type/i18n/es_AR.po
odoo/addons/helpdesk_type/i18n/fr.po
odoo/addons/helpdesk_type/i18n/helpdesk_type.pot
odoo/addons/helpdesk_type/i18n/it.po
odoo/addons/helpdesk_type/i18n/lv.po
odoo/addons/helpdesk_type/i18n/pt.po
odoo/addons/helpdesk_type/i18n/pt_BR.po
odoo/addons/helpdesk_type/i18n/sv.po
odoo/addons/helpdesk_type/i18n/tr.po
odoo/addons/helpdesk_type/models/__init__.py
odoo/addons/helpdesk_type/models/helpdesk_ticket.py
odoo/addons/helpdesk_type/models/helpdesk_ticket_team.py
odoo/addons/helpdesk_type/models/helpdesk_ticket_type.py
odoo/addons/helpdesk_type/models/res_company.py
odoo/addons/helpdesk_type/models/res_config_settings.py
odoo/addons/helpdesk_type/readme/CONFIGURE.md
odoo/addons/helpdesk_type/readme/CONTRIBUTORS.md
odoo/addons/helpdesk_type/readme/DESCRIPTION.md
odoo/addons/helpdesk_type/readme/USAGE.md
odoo/addons/helpdesk_type/security/ir.model.access.csv
odoo/addons/helpdesk_type/static/description/icon.png
odoo/addons/helpdesk_type/static/description/index.html
odoo/addons/helpdesk_type/tests/__init__.py
odoo/addons/helpdesk_type/tests/test_helpdesk_type.py
odoo/addons/helpdesk_type/views/helpdesk_ticket.xml
odoo/addons/helpdesk_type/views/helpdesk_ticket_team.xml
odoo/addons/helpdesk_type/views/helpdesk_ticket_templates.xml
odoo/addons/helpdesk_type/views/helpdesk_ticket_type.xml
odoo/addons/helpdesk_type/views/res_config_settings_views.xml
odoo_addon_helpdesk_type-18.0.1.2.1.4.dist-info/METADATA
odoo_addon_helpdesk_type-18.0.1.2.1.4.dist-info/WHEEL
odoo_addon_helpdesk_type-18.0.1.2.1.4.dist-info/top_level.txt
odoo_addon_helpdesk_type-18.0.1.2.1.4.dist-info/RECORD
